uppaal_creator/__init__.py
uppaal_creator/common.py
uppaal_creator/creator.py
uppaal_creator/layout_computation.py
uppaal_creator-0.1.0.dist-info/METADATA
uppaal_creator-0.1.0.dist-info/WHEEL
uppaal_creator-0.1.0.dist-info/top_level.txt
uppaal_creator-0.1.0.dist-info/RECORD
