Metadata-Version: 2.1
Name: uppaal-creator
Version: 0.1.0
Requires-Python: >=3.10
Requires-Dist: pyuppaal
Requires-Dist: networkx
Requires-Dist: pydot
